Workbook
Name Salário: Planilha1!$E$4

Sheet Planilha1
C3: Configurações
C4: Salário | E4: 4200
C5: Rendimento carteira | E5: 0.006
C6: Sugestão de investimento (30%) | E6: =E4*0.3 -> 1260
C8: Investimento mensal
C9: Valor investido mensal | E9: 1260
C10: Anos de investimento | E10: 10
C11: Taxa de rendimento mensal | E11: 0.01079
C12: Total de patrimônio adquirido | E12: =FV(E11,E10*12,E9*-1) -> 306538.11
C13: Dividendo mensal | E13: =E12*E5 -> 1839.2286
C15: Cenários | E15: Dividendo
B16: 2 | C16: Em 2 anos | D16: =FV($E$11,B16*12,$E$9*-1,) -> 34306.81 | E16: =D16*$E$5 -> 205.84086
B17: 5 | C17: Em 5 anos | D17: =FV($E$11,B17*12,$E$9*-1,) -> 105558.91 | E17: =D17*$E$5 -> 633.35347
B18: 10 | C18: Em 10 anos | D18: =FV($E$11,B18*12,$E$9*-1,) -> 306538.11 | E18: =D18*$E$5 -> 1839.2286
B19: 20 | C19: Em 20 anos | D19: =FV($E$11,B19*12,$E$9*-1,) -> 1417750 | E19: =D19*$E$5 -> 8506.4999
B20: 30 | C20: Em 30 anos | D20: =FV($E$11,B20*12,$E$9*-1,) -> 5445933.8 | E20: =D20*$E$5 -> 32675.603
C22: Perfil | E22: Moderado
C23: Valor a ser investido por mês | E23: =E9 -> 1260
C25: Tipos de FII | D25: Percentual sugerido | E25: Valores
C26: PAPEL | D26: =VLOOKUP($E$22&"-"&C26,Planilha2!$B:$E,4,FALSE) -> 0.32 | E26: =$E$23*D26 -> 403.2
C27: TIJOLO | D27: =VLOOKUP($E$22&"-"&C27,Planilha2!$B:$E,4,FALSE) -> 0.35 | E27: =$E$23*D27 -> 441
C28: HIBRIDOS | D28: =VLOOKUP($E$22&"-"&C28,Planilha2!$B:$E,4,FALSE) -> 0.08 | E28: =$E$23*D28 -> 100.8
C29: FOFs | D29: =VLOOKUP($E$22&"-"&C29,Planilha2!$B:$E,4,FALSE) -> 0.05 | E29: =$E$23*D29 -> 63
C30: DESENVOLVIMENTO | D30: =VLOOKUP($E$22&"-"&C30,Planilha2!$B:$E,4,FALSE) -> 0.1 | E30: =$E$23*D30 -> 126
C31: HOTELARIAS | D31: =VLOOKUP($E$22&"-"&C31,Planilha2!$B:$E,4,FALSE) -> 0.1 | E31: =$E$23*D31 -> 126
C32: Total | E32: =SUM(E26:E31) -> 1260

Sheet Planilha2
B7: CHAVE | C7: PERFIL | D7: TIPO DE FFI | E7: % | G7: CHAVE | H7: %
B8: =C8&"-"&D8 -> Consevador-PAPEL | C8: Consevador | D8: PAPEL | E8: 0.3 | G8: Consevador-TIJOLO | H8: =VLOOKUP(G8,$B:$E,4,FALSE) -> 0.5
B9: =C9&"-"&D9 -> Consevador-TIJOLO | C9: Consevador | D9: TIJOLO | E9: 0.5
B10: =C10&"-"&D10 -> Consevador-HIBRIDOS | C10: Consevador | D10: HIBRIDOS | E10: 0.1
B11: =C11&"-"&D11 -> Consevador-FOFs | C11: Consevador | D11: FOFs | E11: 0.1
B12: =C12&"-"&D12 -> Consevador-DESENVOLVIMENTO | C12: Consevador | D12: DESENVOLVIMENTO | E12: 0
B13: =C13&"-"&D13 -> Consevador-HOTELARIAS | C13: Consevador | D13: HOTELARIAS | E13: 0
B14: =C14&"-"&D14 -> Moderado-PAPEL | C14: Moderado | D14: PAPEL | E14: 0.32
B15: =C15&"-"&D15 -> Moderado-TIJOLO | C15: Moderado | D15: TIJOLO | E15: 0.35
B16: =C16&"-"&D16 -> Moderado-HIBRIDOS | C16: Moderado | D16: HIBRIDOS | E16: 0.08
B17: =C17&"-"&D17 -> Moderado-FOFs | C17: Moderado | D17: FOFs | E17: 0.05
B18: =C18&"-"&D18 -> Moderado-DESENVOLVIMENTO | C18: Moderado | D18: DESENVOLVIMENTO | E18: 0.1
B19: =C19&"-"&D19 -> Moderado-HOTELARIAS | C19: Moderado | D19: HOTELARIAS | E19: 0.1
B20: =C20&"-"&D20 -> Agressivo-PAPEL | C20: Agressivo | D20: PAPEL | E20: 0.5
... B25: =C25&"-"&D25 -> Agressivo-HOTELARIAS | C25: Agressivo | D25: HOTELARIAS | E25: 0.1
